hkmeans_minibatch/__init__.py
hkmeans_minibatch/__main__.py
hkmeans_minibatch/hkmeans.py
hkmeans_minibatch-1.0.2.dist-info/LICENSE
hkmeans_minibatch-1.0.2.dist-info/METADATA
hkmeans_minibatch-1.0.2.dist-info/WHEEL
hkmeans_minibatch-1.0.2.dist-info/top_level.txt
hkmeans_minibatch-1.0.2.dist-info/RECORD
