Metadata-Version: 2.1
Name: hkmeans-minibatch
Version: 1.0.2
Summary: An implementation of hierarchical minibatch kmeans
Home-page: https://github.com/ammesatyajit/heirarchical-minibatch-kmeans
Author: Satyajit Kumar
Author-email: ammesatyajit@gmail.com
License: UNKNOWN
Platform: UNKNOWN
Classifier: Programming Language :: Python :: 3
Classifier: License :: OSI Approved :: Apache Software License
Classifier: Operating System :: OS Independent
Requires-Python: >=3.6
Requires-Dist: numpy
Requires-Dist: tqdm
Requires-Dist: scikit-learn
